README.md
setup.py
pyhot/__init__.py
pyhot/pyhot.py
pyhot.egg-info/PKG-INFO
pyhot.egg-info/SOURCES.txt
pyhot.egg-info/dependency_links.txt
pyhot.egg-info/top_level.txt