Metadata-Version: 1.2
Name: pyhot
Version: 1.0.1
Summary: UNKNOWN
Home-page: UNKNOWN
Author: hw
Author-email: 811417477@qq.com
Maintainer: hw
Maintainer-email: 811417477@qq.com
License: UNKNOWN
Platform: UNKNOWN
Classifier: Programming Language :: Python
Requires-Python: >=3.4
